idjwi/__init__.py
idjwi/functions.py
idjwi-0.1.1.dist-info/METADATA
idjwi-0.1.1.dist-info/WHEEL
idjwi-0.1.1.dist-info/top_level.txt
idjwi-0.1.1.dist-info/RECORD
